django_modeltree-0.9.dist-info/licenses/LICENCE
modeltree/__init__.py
modeltree/__version__.py
modeltree/modeltree.py
django_modeltree-0.9.dist-info/METADATA
django_modeltree-0.9.dist-info/WHEEL
django_modeltree-0.9.dist-info/top_level.txt
django_modeltree-0.9.dist-info/zip-safe
django_modeltree-0.9.dist-info/RECORD
